python_package_info/__init__.py
python_package_info/_cli.py
python_package_info/_main.py
python_package_info-0.0.19.dist-info/licenses/LICENSE
python_package_info-0.0.19.dist-info/METADATA
python_package_info-0.0.19.dist-info/WHEEL
python_package_info-0.0.19.dist-info/entry_points.txt
python_package_info-0.0.19.dist-info/top_level.txt
python_package_info-0.0.19.dist-info/RECORD
